LICENSE
README.md
setup.cfg
setup.py
nncore/__init__.py
nncore.egg-info/PKG-INFO
nncore.egg-info/SOURCES.txt
nncore.egg-info/dependency_links.txt
nncore.egg-info/requires.txt
nncore.egg-info/top_level.txt
nncore/dataset/__init__.py
nncore/dataset/base.py
nncore/dataset/builder.py
nncore/dataset/wrapper.py
nncore/engine/__init__.py
nncore/engine/buffer.py
nncore/engine/builder.py
nncore/engine/comm.py
nncore/engine/engine.py
nncore/engine/utils.py
nncore/engine/hooks/__init__.py
nncore/engine/hooks/base.py
nncore/engine/hooks/checkpoint.py
nncore/engine/hooks/closure.py
nncore/engine/hooks/eval.py
nncore/engine/hooks/lr_updater.py
nncore/engine/hooks/memory.py
nncore/engine/hooks/optimizer.py
nncore/engine/hooks/precise_bn.py
nncore/engine/hooks/sampler_seed.py
nncore/engine/hooks/timer.py
nncore/engine/hooks/writer.py
nncore/image/__init__.py
nncore/image/colorspace.py
nncore/image/geometric.py
nncore/image/io.py
nncore/image/normalize.py
nncore/io/__init__.py
nncore/io/io.py
nncore/io/handlers/__init__.py
nncore/io/handlers/base.py
nncore/io/handlers/hdf5.py
nncore/io/handlers/json.py
nncore/io/handlers/numpy.py
nncore/io/handlers/pickle.py
nncore/io/handlers/txt.py
nncore/io/handlers/xml.py
nncore/io/handlers/yaml.py
nncore/nn/__init__.py
nncore/nn/builder.py
nncore/nn/init.py
nncore/nn/utils.py
nncore/nn/blocks/__init__.py
nncore/nn/blocks/activation.py
nncore/nn/blocks/conv.py
nncore/nn/blocks/msg_pass.py
nncore/nn/blocks/norm.py
nncore/nn/blocks/scale.py
nncore/nn/blocks/transformer.py
nncore/nn/bundle/__init__.py
nncore/nn/bundle/bundle.py
nncore/nn/losses/__init__.py
nncore/nn/losses/bce.py
nncore/nn/losses/contrastive.py
nncore/nn/losses/focal.py
nncore/nn/losses/ghm.py
nncore/nn/losses/lasso.py
nncore/nn/losses/utils.py
nncore/nn/modules/__init__.py
nncore/nn/modules/conv.py
nncore/nn/modules/linear.py
nncore/nn/modules/msg_pass.py
nncore/ops/__init__.py
nncore/ops/bbox.py
nncore/ops/matrix.py
nncore/ops/temporal.py
nncore/optim/__init__.py
nncore/optim/builder.py
nncore/optim/lamb.py
nncore/parallel/__init__.py
nncore/parallel/collate.py
nncore/parallel/container.py
nncore/parallel/parallel.py
