Metadata-Version: 2.4
Name: nncore
Version: 0.4.6
Summary: A lightweight machine learning toolkit for researchers.
Home-page: https://github.com/yeliudev/nncore
Author: Ye Liu
Author-email: yeliudev@outlook.com
License: MIT
Classifier: Development Status :: 4 - Beta
Classifier: License :: OSI Approved :: MIT License
Classifier: Operating System :: OS Independent
Classifier: Programming Language :: Python :: 3
Classifier: Programming Language :: Python :: 3.9
Classifier: Programming Language :: Python :: 3.10
Classifier: Programming Language :: Python :: 3.11
Classifier: Programming Language :: Python :: 3.12
Classifier: Topic :: Utilities
Requires-Python: >=3.9
License-File: LICENSE
Requires-Dist: h5py>=3.10
Requires-Dist: joblib>=1.3
Requires-Dist: jsonlines>=4
Requires-Dist: numpy>=1.26
Requires-Dist: opencv-python>=4.9
Requires-Dist: pyyaml>=6
Requires-Dist: requests>=2.31
Requires-Dist: tabulate>=0.9
Requires-Dist: tensorboard>=2.16
Requires-Dist: termcolor>=2.4
Provides-Extra: docs
Requires-Dist: sphinx-rtd-theme; extra == "docs"
Dynamic: author
Dynamic: author-email
Dynamic: classifier
Dynamic: description
Dynamic: description-content-type
Dynamic: home-page
Dynamic: license
Dynamic: license-file
Dynamic: provides-extra
Dynamic: requires-dist
Dynamic: requires-python
Dynamic: summary
